pytonconnect/__init__.py
pytonconnect/_ton_connect.py
pytonconnect/_wallets_list_manager.py
pytonconnect/exceptions.py
pytonconnect/logger.py
pytonconnect/crypto/__init__.py
pytonconnect/crypto/_session_crypto.py
pytonconnect/parsers/__init__.py
pytonconnect/parsers/_connect_event.py
pytonconnect/parsers/_rpc_parser.py
pytonconnect/parsers/_send_transaction.py
pytonconnect/provider/__init__.py
pytonconnect/provider/_bridge_gateway.py
pytonconnect/provider/_bridge_provider.py
pytonconnect/provider/_bridge_session.py
pytonconnect/provider/_provider.py
pytonconnect/storage/__init__.py
pytonconnect/storage/_default_storage.py
pytonconnect/storage/_file_storage.py
pytonconnect/storage/_interface.py
pytonconnect/storage/redis_storage.py
pytonconnect-0.3.1.dist-info/LICENSE
pytonconnect-0.3.1.dist-info/METADATA
pytonconnect-0.3.1.dist-info/WHEEL
pytonconnect-0.3.1.dist-info/top_level.txt
pytonconnect-0.3.1.dist-info/RECORD
